{"otherData": {},"traceEvents":[{},{"cat":"function","dur":774625,"name":"glfwInit","ph":"X","pid":0,"tid":23808,"ts":184983803732.300},{"cat":"function","dur":381331,"name":"glfwCreateWindow","ph":"X","pid":0,"tid":23808,"ts":184984628039.400},{"cat":"function","dur":2784,"name":"void __cdecl Hazel::OpenGLContext::Init(void)","ph":"X","pid":0,"tid":23808,"ts":184985009697.500},{"cat":"function","dur":20,"name":"void __cdecl Hazel::WindowsWindow::SetVSync(bool)","ph":"X","pid":0,"tid":23808,"ts":184985012617.500},{"cat":"function","dur":1217020,"name":"void __cdecl Hazel::WindowsWindow::Init(const struct Hazel::WindowProps &)","ph":"X","pid":0,"tid":23808,"ts":184983795717.600},{"cat":"function","dur":1217125,"name":"__cdecl Hazel::WindowsWindow::WindowsWindow(const struct Hazel::WindowProps &)","ph":"X","pid":0,"tid":23808,"ts":184983795713.100},{"cat":"function","dur":86592,"name":"void __cdecl Hazel::OpenGLRendererAPI::Init(void)","ph":"X","pid":0,"tid":23808,"ts":184985127144.200},{"cat":"function","dur":9521,"name":"__cdecl Hazel::OpenGLVertexArray::OpenGLVertexArray(void)","ph":"X","pid":0,"tid":23808,"ts":184985213909.600},{"cat":"function","dur":40027,"name":"__cdecl Hazel::OpenGLVertexBuffer::OpenGLVertexBuffer(float *,unsigned int)","ph":"X","pid":0,"tid":23808,"ts":184985223656.700},{"cat":"function","dur":1,"name":"void __cdecl Hazel::OpenGLVertexBuffer::Bind(void) const","ph":"X","pid":0,"tid":23808,"ts":184985312212.000},{"cat":"function","dur":66404,"name":"void __cdecl Hazel::OpenGLVertexArray::AddVertexBuffer(const class std::shared_ptr<class Hazel::VertexBuffer> &)","ph":"X","pid":0,"tid":23808,"ts":184985312183.000},{"cat":"function","dur":138,"name":"__cdecl Hazel::OpenGLIndexBuffer::OpenGLIndexBuffer(unsigned int *,unsigned int)","ph":"X","pid":0,"tid":23808,"ts":184985378706.600},{"cat":"function","dur":1,"name":"void __cdecl Hazel::OpenGLIndexBuffer::Bind(void) const","ph":"X","pid":0,"tid":23808,"ts":184985378915.900},{"cat":"function","dur":68,"name":"void __cdecl Hazel::OpenGLVertexArray::SetIndexBuffer(const class std::shared_ptr<class Hazel::IndexBuffer> &)","ph":"X","pid":0,"tid":23808,"ts":184985378904.300},{"cat":"function","dur":12609,"name":"__cdecl Hazel::OpenGLTexture2D::OpenGLTexture2D(unsigned int,unsigned int)","ph":"X","pid":0,"tid":23808,"ts":184985379032.300},{"cat":"function","dur":145739,"name":"void __cdecl Hazel::OpenGLTexture2D::SetData(void *,unsigned int)","ph":"X","pid":0,"tid":23808,"ts":184985391765.800},{"cat":"function","dur":68473,"name":"class std::basic_string<char,struct std::char_traits<char>,class std::allocator<char> > __cdecl Hazel::OpenGLShader::ReadFile(const class std::basic_string<char,struct std::char_traits<char>,class std::allocator<char> > &)","ph":"X","pid":0,"tid":23808,"ts":184985538151.800},{"cat":"function","dur":2450,"name":"class std::unordered_map<unsigned int,class std::basic_string<char,struct std::char_traits<char>,class std::allocator<char> >,struct std::hash<unsigned int>,struct std::equal_to<unsigned int>,class std::allocator<struct std::pair<unsigned int const ,class std::basic_string<char,struct std::char_traits<char>,class std::allocator<char> > > > > __cdecl Hazel::OpenGLShader::PreProcess(const class std::basic_string<char,struct std::char_traits<char>,class std::allocator<char> > &)","ph":"X","pid":0,"tid":23808,"ts":184985606848.700},{"cat":"function","dur":2153214,"name":"void __cdecl Hazel::OpenGLShader::Compile(const class std::unordered_map<unsigned int,class std::basic_string<char,struct std::char_traits<char>,class std::allocator<char> >,struct std::hash<unsigned int>,struct std::equal_to<unsigned int>,class std::allocator<struct std::pair<unsigned int const ,class std::basic_string<char,struct std::char_traits<char>,class std::allocator<char> > > > > &)","ph":"X","pid":0,"tid":23808,"ts":184985609395.600},{"cat":"function","dur":2224656,"name":"__cdecl Hazel::OpenGLShader::OpenGLShader(const class std::basic_string<char,struct std::char_traits<char>,class std::allocator<char> > &)","ph":"X","pid":0,"tid":23808,"ts":184985538146.900},{"cat":"function","dur":71315,"name":"void __cdecl Hazel::OpenGLShader::Bind(void) const","ph":"X","pid":0,"tid":23808,"ts":184987762945.400},{"cat":"function","dur":31,"name":"void __cdecl Hazel::OpenGLShader::SetInt(const class std::basic_string<char,struct std::char_traits<char>,class std::allocator<char> > &,int)","ph":"X","pid":0,"tid":23808,"ts":184987834400.100},{"cat":"function","dur":2620650,"name":"void __cdecl Hazel::Renderer2D::Init(void)","ph":"X","pid":0,"tid":23808,"ts":184985213848.800},{"cat":"function","dur":2707460,"name":"void __cdecl Hazel::Renderer::Init(void)","ph":"X","pid":0,"tid":23808,"ts":184985127094.700},{"cat":"function","dur":161197,"name":"void __cdecl Hazel::ImGuiLayer::OnAttach(void)","ph":"X","pid":0,"tid":23808,"ts":184987834619.300},{"cat":"function","dur":161324,"name":"void __cdecl Hazel::Application::PushOverlay(class Hazel::Layer *)","ph":"X","pid":0,"tid":23808,"ts":184987834607.800},{"cat":"function","dur":4200301,"name":"__cdecl Hazel::Application::Application(void)","ph":"X","pid":0,"tid":23808,"ts":184983795679.700},{"cat":"function","dur":3,"name":"__cdecl Hazel::OrthographicCamera::OrthographicCamera(float,float,float,float)","ph":"X","pid":0,"tid":23808,"ts":184987996052.900},{"cat":"function","dur":19322,"name":"stbi_load - OpenGLTexture2D::OpenGLTexture2D(const std:string&)","ph":"X","pid":0,"tid":23808,"ts":184987996128.700},{"cat":"function","dur":128698,"name":"__cdecl Hazel::OpenGLTexture2D::OpenGLTexture2D(const class std::basic_string<char,struct std::char_traits<char>,class std::allocator<char> > &)","ph":"X","pid":0,"tid":23808,"ts":184987996128.500},{"cat":"function","dur":129168,"name":"void __cdecl Sandbox2D::OnAttach(void)","ph":"X","pid":0,"tid":23808,"ts":184987996117.700},{"cat":"function","dur":129275,"name":"void __cdecl Hazel::Application::PushLayer(class Hazel::Layer *)","ph":"X","pid":0,"tid":23808,"ts":184987996105.200}]}